pulumi_commandx/__init__.py
pulumi_commandx/_utilities.py
pulumi_commandx/provider.py
pulumi_commandx/pulumi-plugin.json
pulumi_commandx/py.typed
pulumi_commandx/remote/__init__.py
pulumi_commandx/remote/_enums.py
pulumi_commandx/remote/_inputs.py
pulumi_commandx/remote/chmod.py
pulumi_commandx/remote/curl.py
pulumi_commandx/remote/etcdctl.py
pulumi_commandx/remote/hostnamectl.py
pulumi_commandx/remote/mkdir.py
pulumi_commandx/remote/mktemp.py
pulumi_commandx/remote/mv.py
pulumi_commandx/remote/outputs.py
pulumi_commandx/remote/rm.py
pulumi_commandx/remote/sed.py
pulumi_commandx/remote/systemctl.py
pulumi_commandx/remote/tar.py
pulumi_commandx/remote/tee.py
pulumi_commandx/remote/wget.py
pulumi_commandx-0.1.2.dist-info/METADATA
pulumi_commandx-0.1.2.dist-info/WHEEL
pulumi_commandx-0.1.2.dist-info/top_level.txt
pulumi_commandx-0.1.2.dist-info/RECORD
