Metadata-Version: 2.1
Name: pulumi_commandx
Version: 0.1.2
Summary: A Pulumi component provider for creating statically typed `Command` resources.
License: Apache-2.0
Project-URL: Repository, https://github.com/UnstoppableMango/pulumi-commandx
Keywords: pulumi,command,category/utility,kind/component
Requires-Python: >=3.8
Requires-Dist: parver >=0.2.1
Requires-Dist: pulumi <4.0.0,>=3.91.1
Requires-Dist: pulumi-command <1.0.0,>=0.11.1
Requires-Dist: semver >=2.8.1
